search_fs/__init__.py
search_fs/create_db.py
search_fs/search.py
search_fs/web.py
search_fs-0.0.6.post1.dist-info/LICENSE
search_fs-0.0.6.post1.dist-info/METADATA
search_fs-0.0.6.post1.dist-info/WHEEL
search_fs-0.0.6.post1.dist-info/entry_points.txt
search_fs-0.0.6.post1.dist-info/top_level.txt
search_fs-0.0.6.post1.dist-info/zip-safe
search_fs-0.0.6.post1.dist-info/RECORD
