Metadata-Version: 2.1
Name: search-fs
Version: 0.0.6.post1
Summary: Scripts for managing media
Home-page: https://github.com/raydouglass/search-fs
Author: Ray Douglass
Author-email: ray@raydouglass.com
License: Apache
Classifier: Programming Language :: Python :: 3
Classifier: License :: OSI Approved :: Apache Software License
Classifier: Operating System :: OS Independent
Requires-Python: >=3.6
License-File: LICENSE
